goofi/__init__.py
goofi/connection.py
goofi/convenience.py
goofi/data.py
goofi/doc_utils.py
goofi/manager.py
goofi/message.py
goofi/node.py
goofi/node_helpers.py
goofi/params.py
goofi/assets/.gitignore
goofi/assets/__init__.py
goofi/assets/air_elements_filtered.csv
goofi/assets/audio_tags_structure.pkl
goofi/assets/earth.npy
goofi/assets/goofi.ico
goofi/assets/nfixer.pt
goofi/assets/nrealfixer.pt
goofi/assets/peaks_sun_circumsolar_prom0-05.csv
goofi/assets/peaks_sun_extraterrestrial_prom0-05.csv
goofi/assets/planets_peaks.csv
goofi/assets/planets_peaks_long.csv
goofi/assets/planets_peaks_prominence02.csv
goofi/gui/__init__.py
goofi/gui/data_viewer.py
goofi/gui/events.py
goofi/gui/window.py
goofi/nodes/__init__.py
goofi/nodes/analysis/__init__.py
goofi/nodes/analysis/accelerometer.py
goofi/nodes/analysis/audio2txt.py
goofi/nodes/analysis/audiotagging.py
goofi/nodes/analysis/avalanches.py
goofi/nodes/analysis/binarize.py
goofi/nodes/analysis/bioelements.py
goofi/nodes/analysis/bioplanets.py
goofi/nodes/analysis/biorhythms.py
goofi/nodes/analysis/biotuner.py
goofi/nodes/analysis/cardiacrespiration.py
goofi/nodes/analysis/cardiorespiratoryvariability.py
goofi/nodes/analysis/classifier.py
goofi/nodes/analysis/clustering.py
goofi/nodes/analysis/compass.py
goofi/nodes/analysis/connectivity.py
goofi/nodes/analysis/coord2loc.py
goofi/nodes/analysis/correlation.py
goofi/nodes/analysis/dimensionalityreduction.py
goofi/nodes/analysis/dissonancecurve.py
goofi/nodes/analysis/dreaminceptor.py
goofi/nodes/analysis/eegembedding.py
goofi/nodes/analysis/eigendecomposition.py
goofi/nodes/analysis/embedding.py
goofi/nodes/analysis/erp.py
goofi/nodes/analysis/facialexpression.py
goofi/nodes/analysis/fractality.py
goofi/nodes/analysis/gemma3naudio.py
goofi/nodes/analysis/graphmetrics.py
goofi/nodes/analysis/harmonicspectrum.py
goofi/nodes/analysis/img2txt.py
goofi/nodes/analysis/lempelziv.py
goofi/nodes/analysis/monolith.py
goofi/nodes/analysis/pca.py
goofi/nodes/analysis/phiid.py
goofi-2.3.0.dist-info/licenses/LICENSE
goofi-2.3.0.dist-info/METADATA
goofi-2.3.0.dist-info/WHEEL
goofi-2.3.0.dist-info/entry_points.txt
goofi-2.3.0.dist-info/top_level.txt
goofi-2.3.0.dist-info/RECORD
