Metadata-Version: 2.4
Name: goofi
Version: 2.3.0
Summary: Real-time neuro-/biosignal processing and streaming pipeline.
License: MIT License
Keywords: signal-processing,neurofeedback,biofeedback,real-time,EEG,ECG
Classifier: Programming Language :: Python :: 3.9
Classifier: Programming Language :: Python :: 3.10
Classifier: Programming Language :: Python :: 3.11
Classifier: Programming Language :: Python :: 3.12
Classifier: Operating System :: OS Independent
Classifier: License :: OSI Approved :: MIT License
Requires-Python: <3.13,>=3.9
License-File: LICENSE
Requires-Dist: numpy<2
Requires-Dist: dearpygui
Requires-Dist: mne-lsl
Requires-Dist: antropy
Requires-Dist: biotuner
Requires-Dist: pyserial
Requires-Dist: oscpy
Requires-Dist: python-osc
Requires-Dist: sounddevice
Requires-Dist: openai==1.3.6
Requires-Dist: httpx==0.27.2
Requires-Dist: scikit-learn
Requires-Dist: opencv-python==4.8.0.74
Requires-Dist: pyzmq
Requires-Dist: webcolors>=24
Requires-Dist: pylsl
Requires-Dist: mediapipe
Requires-Dist: librosa==0.9.2
Requires-Dist: panns_inference
Requires-Dist: networkx
Requires-Dist: geopy
Requires-Dist: edgeofpy
Requires-Dist: powerlaw
Requires-Dist: mido
Requires-Dist: pyyaml
Requires-Dist: pyaca
Requires-Dist: pandas
Requires-Dist: fooof
Requires-Dist: umap-learn
Requires-Dist: mss
Requires-Dist: usearch
Requires-Dist: gdown
Requires-Dist: neurodsp
Requires-Dist: safetensors
Requires-Dist: einops
Requires-Dist: neurokit2
Requires-Dist: pywavelets
Requires-Dist: torch
Requires-Dist: transformers
Requires-Dist: accelerate
Requires-Dist: tabulate
Requires-Dist: libcst
Requires-Dist: litellm
Requires-Dist: pyperclip
Dynamic: license-file
